{
  "cachedAtUtc": "2026-07-10T02:10:33.683828+00:00",
  "displayFieldName": "status",
  "features": [
    {
      "attributes": {
        "clustercount": 2,
        "id": null,
        "numpeople": 2,
        "objectid": 67904008,
        "xmaximum": -10036698.2964167,
        "xminimum": -10096808.3754601,
        "ymaximum": 3741537.3522854,
        "yminimum": 3693168.00078655
      },
      "geometry": {
        "x": -90.37232875480197,
        "y": 31.70756419011467
      }
    },
    {
      "attributes": {
        "clustercount": 1,
        "id": "7200404",
        "numpeople": 55,
        "objectid": 67902428,
        "xmaximum": -10036698.2964167,
        "xminimum": -10096808.3754601,
        "ymaximum": 3693168.00078655,
        "yminimum": 3644798.64928771
      },
      "geometry": {
        "x": -90.37165234025684,
        "y": 31.165908276191796
      }
    },
    {
      "attributes": {
        "clustercount": 1,
        "id": "7200627",
        "numpeople": 2,
        "objectid": 67905524,
        "xmaximum": -10277138.6125905,
        "xminimum": -10337248.6916339,
        "ymaximum": 3838276.05528309,
        "yminimum": 3789906.70378425
      },
      "geometry": {
        "x": -92.41656367106842,
        "y": 32.4573285959941
      }
    },
    {
      "attributes": {
        "clustercount": 5,
        "id": null,
        "numpeople": 13,
        "objectid": 67905946,
        "xmaximum": -10036698.2964167,
        "xminimum": -10096808.3754601,
        "ymaximum": 3596429.29778886,
        "yminimum": 3548059.94629001
      },
      "geometry": {
        "x": -90.5199748012223,
        "y": 30.531044168564367
      }
    },
    {
      "attributes": {
        "clustercount": 1,
        "id": "7200202",
        "numpeople": 2,
        "objectid": 67905854,
        "xmaximum": -10217028.533547,
        "xminimum": -10277138.6125905,
        "ymaximum": 3886645.40678194,
        "yminimum": 3838276.05528309
      },
      "geometry": {
        "x": -91.95809508029146,
        "y": 32.60729843264472
      }
    },
    {
      "attributes": {
        "clustercount": 1,
        "id": "7200406",
        "numpeople": 1,
        "objectid": 67902493,
        "xmaximum": -10217028.533547,
        "xminimum": -10277138.6125905,
        "ymaximum": 3596429.29778886,
        "yminimum": 3548059.94629001
      },
      "geometry": {
        "x": -92.22999525016094,
        "y": 30.410186952298588
      }
    },
    {
      "attributes": {
        "clustercount": 4,
        "id": null,
        "numpeople": 30,
        "objectid": 67905085,
        "xmaximum": -9976588.21737324,
        "xminimum": -10036698.2964167,
        "ymaximum": 3499690.59479117,
        "yminimum": 3451321.24329232
      },
      "geometry": {
        "x": -90.04386822988796,
        "y": 29.86671477028505
      }
    },
    {
      "attributes": {
        "clustercount": 1,
        "id": "7200420",
        "numpeople": 1,
        "objectid": 67905870,
        "xmaximum": -10217028.533547,
        "xminimum": -10277138.6125905,
        "ymaximum": 3838276.05528309,
        "yminimum": 3789906.70378425
      },
      "geometry": {
        "x": -92.25653388311888,
        "y": 32.23674653200645
      }
    },
    {
      "attributes": {
        "clustercount": 1,
        "id": "7200645",
        "numpeople": 1,
        "objectid": 67905743,
        "xmaximum": -9976588.21737324,
        "xminimum": -10036698.2964167,
        "ymaximum": 3548059.94629001,
        "yminimum": 3499690.59479117
      },
      "geometry": {
        "x": -90.03798222915688,
        "y": 30.003241078486624
      }
    },
    {
      "attributes": {
        "clustercount": 10,
        "id": null,
        "numpeople": 23,
        "objectid": 67905781,
        "xmaximum": -10096808.3754601,
        "xminimum": -10156918.4545036,
        "ymaximum": 3596429.29778886,
        "yminimum": 3548059.94629001
      },
      "geometry": {
        "x": -91.06747089576267,
        "y": 30.506838044183795
      }
    },
    {
      "attributes": {
        "clustercount": 2,
        "id": null,
        "numpeople": 10,
        "objectid": 67906012,
        "xmaximum": -10036698.2964167,
        "xminimum": -10096808.3754601,
        "ymaximum": 3499690.59479117,
        "yminimum": 3451321.24329232
      },
      "geometry": {
        "x": -90.46522866319911,
        "y": 29.66209933346241
      }
    },
    {
      "attributes": {
        "clustercount": 2,
        "id": null,
        "numpeople": 4,
        "objectid": 67902303,
        "xmaximum": -10036698.2964167,
        "xminimum": -10096808.3754601,
        "ymaximum": 3548059.94629001,
        "yminimum": 3499690.59479117
      },
      "geometry": {
        "x": -90.29432020179847,
        "y": 30.15044212381972
      }
    },
    {
      "attributes": {
        "clustercount": 2,
        "id": null,
        "numpeople": 2,
        "objectid": 67906033,
        "xmaximum": -10036698.2964167,
        "xminimum": -10096808.3754601,
        "ymaximum": 3838276.05528309,
        "yminimum": 3789906.70378425
      },
      "geometry": {
        "x": -90.22516693338537,
        "y": 32.40763705192443
      }
    },
    {
      "attributes": {
        "clustercount": 2,
        "id": null,
        "numpeople": 11,
        "objectid": 67906034,
        "xmaximum": -10036698.2964167,
        "xminimum": -10096808.3754601,
        "ymaximum": 3644798.64928771,
        "yminimum": 3596429.29778886
      },
      "geometry": {
        "x": -90.5390018336768,
        "y": 31.01359929977284
      }
    },
    {
      "attributes": {
        "clustercount": 4,
        "id": null,
        "numpeople": 60,
        "objectid": 67906035,
        "xmaximum": -10096808.3754601,
        "xminimum": -10156918.4545036,
        "ymaximum": 3548059.94629001,
        "yminimum": 3499690.59479117
      },
      "geometry": {
        "x": -91.10407556289964,
        "y": 30.152586054987086
      }
    },
    {
      "attributes": {
        "clustercount": 1,
        "id": "7200609",
        "numpeople": 4,
        "objectid": 67905645,
        "xmaximum": -10217028.533547,
        "xminimum": -10277138.6125905,
        "ymaximum": 3789906.70378425,
        "yminimum": 3741537.3522854
      },
      "geometry": {
        "x": -92.22492898282253,
        "y": 31.9139505716197
      }
    },
    {
      "attributes": {
        "clustercount": 1,
        "id": "7200421",
        "numpeople": 1,
        "objectid": 67902591,
        "xmaximum": -9916478.13832979,
        "xminimum": -9976588.21737324,
        "ymaximum": 3789906.70378425,
        "yminimum": 3741537.3522854
      },
      "geometry": {
        "x": -89.54925975583693,
        "y": 31.893340831978133
      }
    }
  ],
  "fieldAliases": {
    "clustercount": "clustercount",
    "id": "id",
    "numpeople": "numpeople",
    "objectid": "objectid",
    "xmaximum": "xmaximum",
    "xminimum": "xminimum",
    "ymaximum": "ymaximum",
    "yminimum": "yminimum"
  },
  "fields": [
    {
      "alias": "clustercount",
      "name": "clustercount",
      "type": "esriFieldTypeSmallInteger"
    },
    {
      "alias": "numpeople",
      "name": "numpeople",
      "type": "esriFieldTypeInteger"
    },
    {
      "alias": "objectid",
      "name": "objectid",
      "type": "esriFieldTypeOID"
    },
    {
      "alias": "id",
      "length": 255,
      "name": "id",
      "type": "esriFieldTypeString"
    },
    {
      "alias": "xminimum",
      "name": "xminimum",
      "type": "esriFieldTypeDouble"
    },
    {
      "alias": "xmaximum",
      "name": "xmaximum",
      "type": "esriFieldTypeDouble"
    },
    {
      "alias": "yminimum",
      "name": "yminimum",
      "type": "esriFieldTypeDouble"
    },
    {
      "alias": "ymaximum",
      "name": "ymaximum",
      "type": "esriFieldTypeDouble"
    }
  ],
  "geometryType": "esriGeometryPoint",
  "sourceName": "Entergy outage cluster ArcGIS layer",
  "spatialReference": {
    "latestWkid": 4326,
    "wkid": 4326
  }
}
