{
  "cachedAtUtc": "2026-07-03T23:44:44.659563+00:00",
  "displayFieldName": "status",
  "features": [
    {
      "attributes": {
        "clustercount": 10,
        "id": null,
        "numpeople": 49,
        "objectid": 67568906,
        "xmaximum": -10096808.3754601,
        "xminimum": -10156918.4545036,
        "ymaximum": 3499690.59479117,
        "yminimum": 3451321.24329232
      },
      "geometry": {
        "x": -90.84188258348829,
        "y": 29.79285041172566
      }
    },
    {
      "attributes": {
        "clustercount": 1,
        "id": "7169953",
        "numpeople": 11,
        "objectid": 67568207,
        "xmaximum": -10096808.3754601,
        "xminimum": -10156918.4545036,
        "ymaximum": 3644798.64928771,
        "yminimum": 3596429.29778886
      },
      "geometry": {
        "x": -91.21948021779137,
        "y": 30.844728052915233
      }
    },
    {
      "attributes": {
        "clustercount": 4,
        "id": null,
        "numpeople": 7,
        "objectid": 67570327,
        "xmaximum": -10036698.2964167,
        "xminimum": -10096808.3754601,
        "ymaximum": 3838276.05528309,
        "yminimum": 3789906.70378425
      },
      "geometry": {
        "x": -90.23957559839299,
        "y": 32.27854902048035
      }
    },
    {
      "attributes": {
        "clustercount": 2,
        "id": null,
        "numpeople": 514,
        "objectid": 67569850,
        "xmaximum": -9976588.21737324,
        "xminimum": -10036698.2964167,
        "ymaximum": 3548059.94629001,
        "yminimum": 3499690.59479117
      },
      "geometry": {
        "x": -90.07434054217086,
        "y": 30.002453283507332
      }
    },
    {
      "attributes": {
        "clustercount": 2,
        "id": null,
        "numpeople": 3,
        "objectid": 67558952,
        "xmaximum": -10096808.3754601,
        "xminimum": -10156918.4545036,
        "ymaximum": 3935014.75828079,
        "yminimum": 3886645.40678194
      },
      "geometry": {
        "x": -90.99467034793021,
        "y": 33.059407591937216
      }
    },
    {
      "attributes": {
        "clustercount": 2,
        "id": null,
        "numpeople": 29,
        "objectid": 67569283,
        "xmaximum": -10096808.3754601,
        "xminimum": -10156918.4545036,
        "ymaximum": 3789906.70378425,
        "yminimum": 3741537.3522854
      },
      "geometry": {
        "x": -90.984852277499,
        "y": 32.04408695862286
      }
    },
    {
      "attributes": {
        "clustercount": 1,
        "id": "7169700",
        "numpeople": 57,
        "objectid": 67566590,
        "xmaximum": -10036698.2964167,
        "xminimum": -10096808.3754601,
        "ymaximum": 3789906.70378425,
        "yminimum": 3741537.3522854
      },
      "geometry": {
        "x": -90.45938728066487,
        "y": 32.0588004759555
      }
    },
    {
      "attributes": {
        "clustercount": 1,
        "id": "7170087",
        "numpeople": 5,
        "objectid": 67570363,
        "xmaximum": -10036698.2964167,
        "xminimum": -10096808.3754601,
        "ymaximum": 3644798.64928771,
        "yminimum": 3596429.29778886
      },
      "geometry": {
        "x": -90.51007361213122,
        "y": 30.943043112263283
      }
    },
    {
      "attributes": {
        "clustercount": 1,
        "id": "7169720",
        "numpeople": 8,
        "objectid": 67568591,
        "xmaximum": -10217028.533547,
        "xminimum": -10277138.6125905,
        "ymaximum": 3499690.59479117,
        "yminimum": 3451321.24329232
      },
      "geometry": {
        "x": -91.97981384104395,
        "y": 29.951038588038852
      }
    },
    {
      "attributes": {
        "clustercount": 3,
        "id": null,
        "numpeople": 3,
        "objectid": 67570175,
        "xmaximum": -10036698.2964167,
        "xminimum": -10096808.3754601,
        "ymaximum": 3451321.24329232,
        "yminimum": 3402951.89179347
      },
      "geometry": {
        "x": -90.49146907912854,
        "y": 29.440388187989925
      }
    },
    {
      "attributes": {
        "clustercount": 11,
        "id": null,
        "numpeople": 30,
        "objectid": 67570418,
        "xmaximum": -10096808.3754601,
        "xminimum": -10156918.4545036,
        "ymaximum": 3596429.29778886,
        "yminimum": 3548059.94629001
      },
      "geometry": {
        "x": -91.08903213305868,
        "y": 30.498950068908485
      }
    },
    {
      "attributes": {
        "clustercount": 8,
        "id": null,
        "numpeople": 152,
        "objectid": 67569242,
        "xmaximum": -10096808.3754601,
        "xminimum": -10156918.4545036,
        "ymaximum": 3548059.94629001,
        "yminimum": 3499690.59479117
      },
      "geometry": {
        "x": -91.02194345464116,
        "y": 30.046431584065928
      }
    },
    {
      "attributes": {
        "clustercount": 2,
        "id": null,
        "numpeople": 2,
        "objectid": 67570440,
        "xmaximum": -10096808.3754601,
        "xminimum": -10156918.4545036,
        "ymaximum": 3886645.40678194,
        "yminimum": 3838276.05528309
      },
      "geometry": {
        "x": -91.20442230296031,
        "y": 32.809759526294734
      }
    },
    {
      "attributes": {
        "clustercount": 1,
        "id": "7169902",
        "numpeople": 8,
        "objectid": 67570220,
        "xmaximum": -10217028.533547,
        "xminimum": -10277138.6125905,
        "ymaximum": 3886645.40678194,
        "yminimum": 3838276.05528309
      },
      "geometry": {
        "x": -92.06107413179089,
        "y": 32.63437694878113
      }
    },
    {
      "attributes": {
        "clustercount": 2,
        "id": null,
        "numpeople": 56,
        "objectid": 67568421,
        "xmaximum": -10156918.4545036,
        "xminimum": -10217028.533547,
        "ymaximum": 3838276.05528309,
        "yminimum": 3789906.70378425
      },
      "geometry": {
        "x": -91.47649050627048,
        "y": 32.399637575997424
      }
    },
    {
      "attributes": {
        "clustercount": 2,
        "id": null,
        "numpeople": 2,
        "objectid": 67570247,
        "xmaximum": -10217028.533547,
        "xminimum": -10277138.6125905,
        "ymaximum": 3838276.05528309,
        "yminimum": 3789906.70378425
      },
      "geometry": {
        "x": -92.09004443043636,
        "y": 32.5461869781923
      }
    },
    {
      "attributes": {
        "clustercount": 5,
        "id": null,
        "numpeople": 7,
        "objectid": 67570483,
        "xmaximum": -10096808.3754601,
        "xminimum": -10156918.4545036,
        "ymaximum": 3838276.05528309,
        "yminimum": 3789906.70378425
      },
      "geometry": {
        "x": -90.85224814619778,
        "y": 32.318864142265426
      }
    },
    {
      "attributes": {
        "clustercount": 6,
        "id": null,
        "numpeople": 26,
        "objectid": 67570484,
        "xmaximum": -9976588.21737324,
        "xminimum": -10036698.2964167,
        "ymaximum": 3499690.59479117,
        "yminimum": 3451321.24329232
      },
      "geometry": {
        "x": -90.03693208740613,
        "y": 29.862634214618286
      }
    },
    {
      "attributes": {
        "clustercount": 1,
        "id": "7170073",
        "numpeople": 1,
        "objectid": 67570509,
        "xmaximum": -10036698.2964167,
        "xminimum": -10096808.3754601,
        "ymaximum": 3596429.29778886,
        "yminimum": 3548059.94629001
      },
      "geometry": {
        "x": -90.36493858279155,
        "y": 30.504769732529578
      }
    },
    {
      "attributes": {
        "clustercount": 3,
        "id": null,
        "numpeople": 32,
        "objectid": 67565898,
        "xmaximum": -10036698.2964167,
        "xminimum": -10096808.3754601,
        "ymaximum": 3499690.59479117,
        "yminimum": 3451321.24329232
      },
      "geometry": {
        "x": -90.49935454867776,
        "y": 29.69692422321591
      }
    },
    {
      "attributes": {
        "clustercount": 2,
        "id": null,
        "numpeople": 4,
        "objectid": 67561728,
        "xmaximum": -10036698.2964167,
        "xminimum": -10096808.3754601,
        "ymaximum": 3548059.94629001,
        "yminimum": 3499690.59479117
      },
      "geometry": {
        "x": -90.29775140034043,
        "y": 30.16750985362753
      }
    }
  ],
  "fieldAliases": {
    "clustercount": "clustercount",
    "id": "id",
    "numpeople": "numpeople",
    "objectid": "objectid",
    "xmaximum": "xmaximum",
    "xminimum": "xminimum",
    "ymaximum": "ymaximum",
    "yminimum": "yminimum"
  },
  "fields": [
    {
      "alias": "clustercount",
      "name": "clustercount",
      "type": "esriFieldTypeSmallInteger"
    },
    {
      "alias": "numpeople",
      "name": "numpeople",
      "type": "esriFieldTypeInteger"
    },
    {
      "alias": "objectid",
      "name": "objectid",
      "type": "esriFieldTypeOID"
    },
    {
      "alias": "id",
      "length": 255,
      "name": "id",
      "type": "esriFieldTypeString"
    },
    {
      "alias": "xminimum",
      "name": "xminimum",
      "type": "esriFieldTypeDouble"
    },
    {
      "alias": "xmaximum",
      "name": "xmaximum",
      "type": "esriFieldTypeDouble"
    },
    {
      "alias": "yminimum",
      "name": "yminimum",
      "type": "esriFieldTypeDouble"
    },
    {
      "alias": "ymaximum",
      "name": "ymaximum",
      "type": "esriFieldTypeDouble"
    }
  ],
  "geometryType": "esriGeometryPoint",
  "sourceName": "Entergy outage cluster ArcGIS layer",
  "spatialReference": {
    "latestWkid": 4326,
    "wkid": 4326
  }
}
